{
  "title": "Agrohorticulture",
  "logoFit": "none",
  "logoPosition": "right",
  "completedHtml": {
    "default": "<h3>Agrohorticulture  has been submitted successfully !</h3>",
    "hi": "<h3>कृषि-बागवानी संबंधी विवरण सफलतापूर्वक जमा कर दिया गया है!</h3>"
  },
  "loadingHtml": {
    "default": "<h3>Loading Agrohorticulture Form...</h3>",
    "hi": "<h3>कृषि-बागवानी विवरण प्रपत्र लोड हो रहा है...</h3>"
  },
  "pages": [
    {
      "name": "page1",
      "elements": [
        {
          "type": "text",
          "name": "beneficiary_settlement",
          "title": {
            "default": "Name of Beneficiary's Settlement",
            "hi": "लाभ मिलने वाला टोला का नाम "
          },
          "isRequired": true
        },
        {
          "type": "radiogroup",
          "name": "select_one_y_n",
          "title": {
            "default": "Are there demands for plantation in the settlement",
            "hi": "क्या बस्ती में वृक्षारोपण की मांग है?"
          },
          "isRequired": true,
          "choices": [
            {
              "value": "Yes",
              "text": {
                "default": "Yes",
                "hi": "हाँ"
              }
            },
            {
              "value": "No",
              "text": {
                "default": "No",
                "hi": "नहीं"
              }
            }
          ]
        },
        {
          "type": "radiogroup",
          "name": "demand_type_plantations",
          "visibleIf": "{select_one_y_n} = 'Yes'",
          "title": {
            "default": "Type of Demand",
            "hi": "मांग का प्रकार"
          },
          "isRequired": true,
          "choices": [
            {
              "value": "Community_demand",
              "text": {
                "default": "Community Demand",
                "hi": "सामुदायिक मांग"
              }
            },
            {
              "value": "Cluster_demand",
              "text": {
                "default": "Cluster Demand",
                "hi": "क्लस्टर मांग"
              }
            },
            {
              "value": "Individual_demand",
              "text": {
                "default": "Individual Demand",
                "hi": "व्यक्तिगत मांग"
              }
            }
          ]
        },
        {
          "type": "text",
          "name": "name_cluster",
          "visibleIf": "{demand_type_plantations} = 'Cluster_demand'",
          "title": {
            "default": "Name of Cluster Group / FPO / SHG\n",
            "hi": "क्लस्टर समूह / परिवार संगठन / स्वयं सहायता समूह का नाम"
          },
          "isRequired": true
        },
        {
          "type": "text",
          "name": "total_cluster",
          "visibleIf": "{demand_type_plantations} = 'Cluster_demand'",
          "title": {
            "default": "Total number of members in the cluster\n",
            "hi": "क्लस्टर में सदस्यों की कुल संख्या"
          },
          "isRequired": true
        },
        {
          "type": "text",
          "name": "question2",
          "visibleIf": "{demand_type_plantations} = 'Individual_demand'",
          "title": {
            "default": "Beneficiary's Name",
            "hi": "लाभार्थी का नाम"
          },
          "isRequired": true
        },
        {
          "type": "radiogroup",
          "name": "gender",
          "visibleIf": "{demand_type_plantations} = 'Individual_demand'",
          "title": {
            "default": "Gender\n",
            "hi": "लिंग"
          },
          "isRequired": true,
          "choices": [
            {
              "value": "Male",
              "text": {
                "default": "Male",
                "hi": "पुरुष"
              }
            },
            {
              "value": "Female",
              "text": {
                "default": "Female",
                "hi": "महिला"
              }
            }
          ]
        },
        {
          "type": "text",
          "name": "ben_father",
          "visibleIf": "{demand_type_plantations} = 'Individual_demand'",
          "title": {
            "default": "Beneficiary's Father/Husband name\n",
            "hi": "लाभार्थी के पिता/पति का नाम"
          },
          "isRequired": true
        },
        {
          "type": "checkbox",
          "name": "select_multiple_species",
          "visibleIf": "{demand_type_plantations} = 'Community_demand' or {demand_type_plantations} = 'Cluster_demand' or {demand_type_plantations} = 'Individual_demand'",
          "title": {
            "default": "Preferred Plant/ species for Plantation",
            "hi": "वृक्षारोपण के लिए पसंदीदा पौधा/प्रजाति"
          },
          "isRequired": true,
          "choices": [
            {
              "value": "Mango",
              "text": {
                "default": "Mango",
                "hi": "आम"
              }
            },
            {
              "value": "Guava",
              "text": {
                "default": "Guava",
                "hi": "अमरूद"
              }
            },
            {
              "value": "Banana",
              "text": {
                "default": "Banana",
                "hi": "केला"
              }
            },
            {
              "value": "Subabul",
              "text": {
                "default": "Subabul",
                "hi": "सुबबुल"
              }
            },
            {
              "value": "Bamboo",
              "text": {
                "default": "Bamboo",
                "hi": "बांस"
              }
            },
            {
              "value": "Moringa",
              "text": {
                "default": "Moringa",
                "hi": "सहजन (मुनगा)"
              }
            },
            {
              "value": "Neem",
              "text": {
                "default": "Neem",
                "hi": "नीम"
              }
            },
            {
              "value": "Teak",
              "text": {
                "default": "Teak",
                "hi": "सागवान"
              }
            },
            {
              "value": "Cashew",
              "text": {
                "default": "Cashew",
                "hi": "काजू"
              }
            },
            {
              "value": "Mahua",
              "text": {
                "default": "Mahua",
                "hi": "महुआ"
              }
            },
            {
              "value": "Tamarind",
              "text": {
                "default": "Tamarind",
                "hi": "इमली"
              }
            },
            {
              "value": "other",
              "text": {
                "default": "Other",
                "hi": "अन्य"
              }
            }
          ]
        },
        {
          "type": "text",
          "name": "select_multiple_species_other",
          "visibleIf": "{select_multiple_species} allof ['other']",
          "title": {
            "default": "Specify other",
            "hi": "अन्य निर्दिष्ट करें"
          }
        },
        {
          "type": "text",
          "name": "crop_area",
          "visibleIf": "{demand_type_plantations} = 'Community_demand' or {demand_type_plantations} = 'Cluster_demand' or {demand_type_plantations} = 'Individual_demand'",
          "title": {
            "default": "Total area of the plantation",
            "hi": "वृक्षारोपण का कुल क्षेत्रफल"
          },
          "description": {
            "default": "Acres",
            "hi": "एकड़"
          },
          "isRequired": true,
          "inputType": "number"
        },
        {
          "type": "text",
          "name": "total_saplings",
          "visibleIf": "{demand_type_plantations} = 'Community_demand' or {demand_type_plantations} = 'Cluster_demand' or {demand_type_plantations} = 'Individual_demand'",
          "title": {
            "default": "Total number of saplings needed",
            "hi": "आवश्यक पौधों की कुल संख्या"
          },
          "isRequired": true,
          "inputType": "number"
        },
        {
          "type": "checkbox",
          "name": "land_type",
          "visibleIf": "{demand_type_plantations} = 'Community_demand' or {demand_type_plantations} = 'Cluster_demand' or {demand_type_plantations} = 'Individual_demand'",
          "title": {
            "default": "Land Type",
            "hi": "भूमि का प्रकार"
          },
          "isRequired": true,
          "choices": [
            {
              "value": "Upland",
              "text": {
                "default": "Upland",
                "hi": "अपलैंड"
              }
            },
            {
              "value": "Midland",
              "text": {
                "default": "Midland",
                "hi": "समुद्र से दूर"
              }
            },
            {
              "value": "Lowland",
              "text": {
                "default": "Lowland",
                "hi": "समतल नीचा भूमि"
              }
            }
          ]
        },
        {
          "type": "radiogroup",
          "name": "land_ownership",
          "visibleIf": "{demand_type_plantations} = 'Community_demand' or {demand_type_plantations} = 'Cluster_demand' or {demand_type_plantations} = 'Individual_demand'",
          "title": {
            "default": "Land Ownership / Tenure",
            "hi": "भूमि स्वामित्व / कार्यकाल"
          },
          "choices": [
            {
              "value": "Own_land",
              "text": {
                "default": "Own land",
                "hi": "अपने देश"
              }
            },
            {
              "value": "Leased_land",
              "text": {
                "default": "Leased land",
                "hi": "पट्टे पर दी गई भूमि"
              }
            },
            {
              "value": "Community_land",
              "text": {
                "default": "Community land",
                "hi": "सामुदायिक भूमि"
              }
            },
            {
              "value": "Forest_land",
              "text": {
                "default": "Forest land",
                "hi": "वन भूमि"
              }
            },
            {
              "value": "Joint_ownership",
              "text": {
                "default": "Joint ownership",
                "hi": "संयुक्त स्वामित्व"
              }
            },
            {
              "value": "other",
              "text": {
                "default": "Other",
                "hi": "अन्य"
              }
            }
          ]
        },
        {
          "type": "text",
          "name": "land_ownership_other",
          "visibleIf": "{land_ownership} = 'other'",
          "title": {
            "default": "Specify other",
            "hi": "अन्य निर्दिष्ट करें"
          }
        },
        {
          "type": "checkbox",
          "name": "current_land_use",
          "visibleIf": "{demand_type_plantations} = 'Community_demand' or {demand_type_plantations} = 'Cluster_demand' or {demand_type_plantations} = 'Individual_demand'",
          "title": {
            "default": "Current Land Use",
            "hi": "वर्तमान भूमि उपयोग"
          },
          "isRequired": true,
          "choices": [
            {
              "value": "Crop",
              "text": {
                "default": "Crop",
                "hi": "काटना"
              }
            },
            {
              "value": "Fallow",
              "text": {
                "default": "Fallow",
                "hi": "परती"
              }
            },
            {
              "value": "Grazing",
              "text": {
                "default": "Grazing",
                "hi": "चराई"
              }
            },
            {
              "value": "Homestead",
              "text": {
                "default": "Homestead",
                "hi": "रियासत"
              }
            }
          ]
        },
        {
          "type": "radiogroup",
          "name": "soil_type",
          "visibleIf": "{demand_type_plantations} = 'Community_demand' or {demand_type_plantations} = 'Cluster_demand' or {demand_type_plantations} = 'Individual_demand'",
          "title": {
            "default": "Soil Type\n",
            "hi": "मिट्टी का प्रकार"
          },
          "isRequired": true,
          "choices": [
            {
              "value": "Sandy",
              "text": {
                "default": "Sandy",
                "hi": "रेतीले"
              }
            },
            {
              "value": "Loam",
              "text": {
                "default": "Loam",
                "hi": "चिकनी बलुई मिट्टी"
              }
            },
            {
              "value": "Red",
              "text": {
                "default": "Red",
                "hi": "लाल"
              }
            },
            {
              "value": "Black",
              "text": {
                "default": "Black",
                "hi": "काली"
              }
            },
            {
              "value": "Rocky",
              "text": {
                "default": "Rocky",
                "hi": "चट्टान का"
              }
            }
          ]
        },
        {
          "type": "radiogroup",
          "name": "water_availability",
          "visibleIf": "{demand_type_plantations} = 'Community_demand' or {demand_type_plantations} = 'Cluster_demand' or {demand_type_plantations} = 'Individual_demand'",
          "title": {
            "default": "Water Availability",
            "hi": "पानी की उपलब्धता"
          },
          "isRequired": true,
          "choices": [
            {
              "value": "Seasonal",
              "text": {
                "default": "Seasonal",
                "hi": "मौसमी"
              }
            },
            {
              "value": "12 Months",
              "text": {
                "default": "12 Months",
                "hi": "12 महीने"
              }
            },
            {
              "value": "No water available",
              "text": {
                "default": "No water available",
                "hi": "पानी उपलब्ध नहीं है"
              }
            }
          ]
        },
        {
          "type": "radiogroup",
          "name": "agro_model",
          "visibleIf": "{demand_type_plantations} = 'Community_demand' or {demand_type_plantations} = 'Cluster_demand' or {demand_type_plantations} = 'Individual_demand'",
          "title": {
            "default": "Preferred agroforestry model",
            "hi": "पसंदीदा कृषि वानिकी मॉडल"
          },
          "isRequired": true,
          "choices": [
            {
              "value": "Boundary_plantation",
              "text": {
                "default": "Boundary plantation",
                "hi": "सीमा वृक्षारोपण"
              }
            },
            {
              "value": "Orchard_development",
              "text": {
                "default": "Orchard development",
                "hi": "बाग विकास"
              }
            },
            {
              "value": "Block_plantation",
              "text": {
                "default": "Block plantation",
                "hi": "ब्लॉक वृक्षारोपण"
              }
            },
            {
              "value": "Silvi_pasture",
              "text": {
                "default": "Silvi-pasture",
                "hi": "सिल्वी-पशुपालन"
              }
            },
            {
              "value": "Homestead_plantation",
              "text": {
                "default": "Homestead plantation",
                "hi": "होमस्टेड प्लांटेशन"
              }
            }
          ]
        },
        {
          "type": "checkbox",
          "name": "departments_converged",
          "visibleIf": "{demand_type_plantations} = 'Community_demand' or {demand_type_plantations} = 'Cluster_demand' or {demand_type_plantations} = 'Individual_demand'",
          "title": {
            "default": "Which departments / schemes may be converged with?",
            "hi": "किन विभागों/योजनाओं का विलय किया जा सकता है?"
          },
          "isRequired": true,
          "choices": [
            {
              "value": "Forest",
              "text": {
                "default": "Forest Department",
                "hi": "वन विभाग"
              }
            },
            {
              "value": "Agri",
              "text": {
                "default": "Agriculture Department",
                "hi": "कृषि विभाग"
              }
            },
            {
              "value": "Horticulture",
              "text": {
                "default": "Horticulture Department",
                "hi": "बागवानी विभाग"
              }
            },
            {
              "value": "MGNREGA",
              "text": {
                "default": "MGNREGA",
                "hi": "एमजीएनआरईजीए"
              }
            },
            {
              "value": "Tribal_welfare",
              "text": {
                "default": "Tribal Welfare Department",
                "hi": "जनजातीय कल्याण विभाग"
              }
            },
            {
              "value": "Panchayati_raj",
              "text": {
                "default": "Panchayati Raj Department",
                "hi": "पंचायती राज विभाग"
              }
            },
            {
              "value": "NRLM",
              "text": {
                "default": "NRLM",
                "hi": "एनआरएलएम"
              }
            },
            {
              "value": "other",
              "text": {
                "default": "Other",
                "hi": "अन्य"
              }
            }
          ]
        },
        {
          "type": "text",
          "name": "departments_converged_other",
          "visibleIf": "{departments_converged} anyof ['other']",
          "title": {
            "default": "Specify other",
            "hi": "अन्य निर्दिष्ट करें"
          }
        },
        {
          "type": "html",
          "name": "rech_strc_note_1",
          "html": {
            "default": "<span style=\"font-size: large; font-weight: bold; color:red;\">DO NOT MODIFY ANYTHING BEYOND THIS POINT AND SUBMIT YOUR FORM DATA</span>",
            "hi": "<span style=\"font-size: large; font-weight: bold; color:red;\">इस बिंदु के बाद कुछ भी न बदलें और अपना फॉर्म डेटा सबमिट करें</span>"
          }
        },
        {
          "type": "multipletext",
          "name": "GPS_point",
          "title": {
            "default": "GPS point to be marked of the area",
            "hi": "उस क्षेत्र का जीपीएस बिंदु चिह्नित किया जाना हैांतर,"
          },
          "readOnly": true,
          "items": [
            {
              "name": "latitude",
              "title": {
                "default": "latitude (x.y °)",
                "hi": "अक्षांश"
              }
            },
            {
              "name": "longitude",
              "title": {
                "default": "longitude (x.y °)",
                "hi": "देशांतर"
              }
            }
          ]
        },
        {
          "type": "text",
          "name": "block_name",
          "title": {
            "default": "Block name",
            "hi": "ब्लॉक का नाम "
          },
          "readOnly": true
        },
        {
          "type": "text",
          "name": "plan_id",
          "title": {
            "default": "Plan ID",
            "hi": "योजना का आईडी"
          },
          "readOnly": true
        },
        {
          "type": "text",
          "name": "plan_name",
          "title": {
            "default": "Plan name",
            "hi": "योजना का नाम "
          },
          "readOnly": true
        },
        {
          "type": "text",
          "name": "user_latlon",
          "title": {
            "default": "Current location of the user",
            "hi": "उपयोगकर्ता का वर्तमान स्थान"
          }
        }
      ]
    }
  ],
  "widthMode": "responsive"
}